django_db_schema_renderer/__init__.py
django_db_schema_renderer/forms.py
django_db_schema_renderer/templates/admin/index.html
django_db_schema_renderer/templates/input.html
django_db_schema_renderer/urls.py
django_db_schema_renderer/views.py
django_db_schema_renderer-0.1.2.dist-info/LICENSE
django_db_schema_renderer-0.1.2.dist-info/WHEEL
django_db_schema_renderer-0.1.2.dist-info/METADATA
django_db_schema_renderer-0.1.2.dist-info/RECORD
