Metadata-Version: 2.1
Name: django-db-schema-renderer
Version: 0.1.2
Summary: Django app to render ER diagram
Author: Oleksandr Korol
Author-email: oleksandr.korol@coaxsoft.com
Requires-Python: >=3.8
Classifier: Programming Language :: Python :: 3
Classifier: Programming Language :: Python :: 3.8
Classifier: Programming Language :: Python :: 3.9
Classifier: Programming Language :: Python :: 3.10
Classifier: Programming Language :: Python :: 3.11
Requires-Dist: Django (>=3.2)
Requires-Dist: django-extensions (>=3.2.1,<4.0.0)
Requires-Dist: pygraphviz (>=1.10,<2.0)
